<?xml version="1.0" encoding="utf-8" ?>
<Referentials>
  <Referential>
    <TableName>INSTRUMENTOF</TableName>
    <Ressource>INSTRUMENTOF</Ressource>
    <ColumnByRow>3</ColumnByRow>
    <Create>true</Create>
    <Modify>true</Modify>
    <Remove>true</Remove>
    <Image></Image>

    <SQLWhere>
      <ConditionSystem>SESSIONRESTRICT</ConditionSystem>
      <SQLJoin>inner join dbo.SESSIONRESTRICT sr on sr.ID=tblmain.IDI_INSTR and sr.CLASS='INSTRUMENT' And sr.SESSIONID='%%SESSIONID%%'</SQLJoin>
      <SQLJoin>inner join dbo.SESSIONRESTRICT sr2 on sr2.ID=tblmain.IDI and sr2.CLASS='INSTRUMENT' And sr2.SESSIONID='%%SESSIONID%%'</SQLJoin>
    </SQLWhere>

    <Column>
      <ColumnName>IDI_INSTR</ColumnName>
      <Ressource>IDI_INSTR</Ressource>
      <DataType>int</DataType>
      <Colspan>3</Colspan>
      <Length>10</Length>
      <Scale>0</Scale>
      <IsMandatory>true</IsMandatory>
      <RegularExpression></RegularExpression>
      <Default></Default>
      <IsHide>false</IsHide>
      <IsHideInDataGrid>false</IsHideInDataGrid>
      <IsDataKeyField>false</IsDataKeyField>
      <IsKeyField>false</IsKeyField>
      <IsForeignKeyField>true</IsForeignKeyField>
      <IsIdentity>false</IsIdentity>
      <IsUpdatable>true</IsUpdatable>
      <IsOrderBy>true</IsOrderBy>
      <Relation>
        <TableName>INSTRUMENT</TableName>
        <AliasTableName>mnu_parent</AliasTableName>
        <ColumnRelation>
          <ColumnName>IDI</ColumnName>
          <DataType>int</DataType>
        </ColumnRelation>
        <ColumnSelect>
          <ColumnName>IDENTIFIER</ColumnName>
          <Ressource>INSTRUMENT_Parent</Ressource>
          <DataType>string</DataType>
        </ColumnSelect>
        <ColumnLabel>
          <ColumnName>DISPLAYNAME</ColumnName>
          <Ressource>DISPLAYNAME</Ressource>
          <DataType>string</DataType>
        </ColumnLabel>
      </Relation>
      <html_BLOCK title="Characteristics" columnbyrow="1" ></html_BLOCK>
    </Column>
    <Column>
      <ColumnName>IDI</ColumnName>
      <Ressource>IDI</Ressource>
      <DataType>int</DataType>
      <Length>10</Length>
      <Scale>0</Scale>
      <IsMandatory>true</IsMandatory>
      <RegularExpression></RegularExpression>
      <Default></Default>
      <IsHide>false</IsHide>
      <IsHideInDataGrid>false</IsHideInDataGrid>
      <IsKeyField>false</IsKeyField>
      <IsDataKeyField>false</IsDataKeyField>
      <IsIdentity>false</IsIdentity>
      <IsUpdatable>true</IsUpdatable>
      <Relation>
        <TableName>INSTRUMENT</TableName>
        <AliasTableName>mnu_child</AliasTableName>
        <ColumnRelation>
          <ColumnName>IDI</ColumnName>
          <DataType>int</DataType>
        </ColumnRelation>
        <ColumnSelect>
          <ColumnName>IDENTIFIER</ColumnName>
          <Ressource>INSTRUMENT_Child</Ressource>
          <DataType>string</DataType>
        </ColumnSelect>
        <ColumnLabel>
          <ColumnName>DISPLAYNAME</ColumnName>
          <Ressource>DISPLAYNAME</Ressource>
          <DataType>string</DataType>
        </ColumnLabel>
      </Relation>
      <html_HR title="Empty" size="2"></html_HR>
    </Column>
    <Column>
      <ColumnName>INSTRUMENTLEVEL</ColumnName>
      <Ressource>INSTRUMENTLEVEL</Ressource>
      <DataType>int</DataType>
      <Align>left</Align>
      <InputWidth>50</InputWidth>
      <Length>5</Length>
      <Scale>0</Scale>
      <IsMandatory>true</IsMandatory>
      <RegularExpression></RegularExpression>
      <Default></Default>
      <IsHide>false</IsHide>
      <IsHideInDataGrid>false</IsHideInDataGrid>
      <IsDataKeyField>false</IsDataKeyField>
      <IsKeyField>false</IsKeyField>
      <IsForeignKeyField>false</IsForeignKeyField>
      <IsIdentity>false</IsIdentity>
      <IsUpdatable>true</IsUpdatable>
      <IsOrderBy>true</IsOrderBy>
      <Relation></Relation>
      <Information>
        <Type>information</Type>
        <LabelMessage>Msg_INSTRUMENTLEVELForINSTRUMENTOF</LabelMessage>
      </Information>
      <html_HR title="Empty" size="1"></html_HR>
    </Column>
    <Column>
      <ColumnName>NBMIN</ColumnName>
      <Ressource>NBMIN</Ressource>
      <DataType>int</DataType>
      <Colspan>3</Colspan>
      <Align>left</Align>
      <InputWidth>50</InputWidth>
      <Length>5</Length>
      <Scale>0</Scale>
      <IsMandatory>true</IsMandatory>
      <RegularExpression></RegularExpression>
      <Default></Default>
      <IsHide>false</IsHide>
      <IsHideInDataGrid>true</IsHideInDataGrid>
      <IsKeyField>false</IsKeyField>
      <IsDataKeyField>false</IsDataKeyField>
      <IsIdentity>false</IsIdentity>
      <IsUpdatable>true</IsUpdatable>
      <Relation></Relation>
      <Information>
        <Type>information</Type>
        <LabelMessage>Msg_NBMINForINSTRUMENTOF</LabelMessage>
      </Information>
      <html_HR title="Instrument_Title" size="1"></html_HR>
    </Column>
    <Column>
      <ColumnName>NBMAX</ColumnName>
      <Ressource>NBMAX</Ressource>
      <DataType>int</DataType>
      <Colspan>3</Colspan>
      <Align>left</Align>
      <InputWidth>50</InputWidth>
      <Length>5</Length>
      <Scale>0</Scale>
      <IsMandatory>false</IsMandatory>
      <RegularExpression></RegularExpression>
      <Default></Default>
      <IsHide>false</IsHide>
      <IsHideInDataGrid>true</IsHideInDataGrid>
      <IsKeyField>false</IsKeyField>
      <IsDataKeyField>false</IsDataKeyField>
      <IsIdentity>false</IsIdentity>
      <IsUpdatable>true</IsUpdatable>
      <Relation></Relation>
      <Information>
        <Type>information</Type>
        <LabelMessage>Msg_NBMAXForINSTRUMENTOF</LabelMessage>
      </Information>
    </Column>
    <Column>
      <ColumnName>ISEVEN</ColumnName>
      <Ressource>ISEVEN</Ressource>
      <DataType>bool</DataType>
      <Colspan>0</Colspan>
      <Length>1</Length>
      <Scale>0</Scale>
      <IsMandatory>true</IsMandatory>
      <RegularExpression></RegularExpression>
      <Default>
        <Value>false</Value>
      </Default>
      <IsHide>false</IsHide>
      <IsHideInDataGrid>true</IsHideInDataGrid>
      <IsDataKeyField>false</IsDataKeyField>
      <IsKeyField>false</IsKeyField>
      <IsForeignKeyField>false</IsForeignKeyField>
      <IsIdentity>false</IsIdentity>
      <IsUpdatable>true</IsUpdatable>
      <Relation></Relation>
      <Information>
        <Type>information</Type>
        <LabelMessage>Msg_ISEVENForINSTRUMENTOF</LabelMessage>
      </Information>
    </Column>
    <Column>
      <ColumnName>ISMAINPRDREF</ColumnName>
      <Ressource>ISMAINPRDREF</Ressource>
      <DataType>bool</DataType>
      <Colspan>3</Colspan>
      <Length>1</Length>
      <Scale>0</Scale>
      <IsMandatory>true</IsMandatory>
      <RegularExpression></RegularExpression>
      <Default>
        <Value>false</Value>
      </Default>
      <IsHide>false</IsHide>
      <IsHideInDataGrid>false</IsHideInDataGrid>
      <IsDataKeyField>false</IsDataKeyField>
      <IsKeyField>false</IsKeyField>
      <IsForeignKeyField>false</IsForeignKeyField>
      <IsIdentity>false</IsIdentity>
      <IsUpdatable>true</IsUpdatable>
      <Relation></Relation>
      <Information>
        <Type>information</Type>
        <LabelMessage>Msg_ISMAINPRDREFForINSTRUMENTOF</LabelMessage>
      </Information>
      <html_HR title="Empty" size="1"></html_HR>
    </Column>
    <Column>
      <ColumnName>ISUNLPRDREF</ColumnName>
      <Ressource>ISUNLPRDREF</Ressource>
      <DataType>bool</DataType>
      <Colspan>3</Colspan>
      <Length>1</Length>
      <Scale>0</Scale>
      <IsMandatory>true</IsMandatory>
      <RegularExpression></RegularExpression>
      <Default>
        <Value>false</Value>
      </Default>
      <IsHide>false</IsHide>
      <IsHideInDataGrid>false</IsHideInDataGrid>
      <IsDataKeyField>false</IsDataKeyField>
      <IsKeyField>false</IsKeyField>
      <IsForeignKeyField>false</IsForeignKeyField>
      <IsIdentity>false</IsIdentity>
      <IsUpdatable>true</IsUpdatable>
      <Relation></Relation>
      <Information>
        <Type>information</Type>
        <LabelMessage>Msg_ISUNLPRDREFForINSTRUMENTOF</LabelMessage>
      </Information>
      <html_HR title="Empty" size="1"></html_HR>
    </Column>
    <Column>
      <ColumnName>DCVALUE</ColumnName>
      <Ressource>DCVALUE</Ressource>
      <Colspan>0</Colspan>
      <DataType>string</DataType>
      <Length>64</Length>
      <Scale>0</Scale>
      <IsMandatory>false</IsMandatory>
      <RegularExpression></RegularExpression>
      <Default></Default>
      <IsHide>false</IsHide>
      <IsHideInDataGrid>false</IsHideInDataGrid>
      <IsDataKeyField>false</IsDataKeyField>
      <IsKeyField>false</IsKeyField>
      <IsForeignKeyField>false</IsForeignKeyField>
      <IsIdentity>false</IsIdentity>
      <IsUpdatable>true</IsUpdatable>
      <!--IsResource>true</IsResource-->
      <Relation>
        <DDLType>enum.DerivativeContractValueEnum</DDLType>
      </Relation>
    </Column>
    <Column>
      <ColumnName>PUTCALLVALUE</ColumnName>
      <Ressource>PUTCALLVALUE</Ressource>
      <Colspan>0</Colspan>
      <DataType>string</DataType>
      <Length>64</Length>
      <Scale>0</Scale>
      <IsMandatory>false</IsMandatory>
      <RegularExpression></RegularExpression>
      <Default></Default>
      <IsHide>false</IsHide>
      <IsHideInDataGrid>false</IsHideInDataGrid>
      <IsDataKeyField>false</IsDataKeyField>
      <IsKeyField>false</IsKeyField>
      <IsForeignKeyField>false</IsForeignKeyField>
      <IsIdentity>false</IsIdentity>
      <IsUpdatable>true</IsUpdatable>
      <!--IsResource>true</IsResource-->
      <Relation>
        <DDLType>enum.PutCallValueEnum</DDLType>
      </Relation>
      <Information>
        <Type>information</Type>
        <LabelMessage>Msg_PUTCALLVALUEForINSTRUMENTOF</LabelMessage>
      </Information>
    </Column>
    <Column>
      <ColumnName>MATURITYVALUE</ColumnName>
      <Ressource>MATURITYVALUE</Ressource>
      <Colspan>0</Colspan>
      <DataType>string</DataType>
      <Length>64</Length>
      <Scale>0</Scale>
      <IsMandatory>false</IsMandatory>
      <RegularExpression></RegularExpression>
      <Default></Default>
      <IsHide>false</IsHide>
      <IsHideInDataGrid>false</IsHideInDataGrid>
      <IsDataKeyField>false</IsDataKeyField>
      <IsKeyField>false</IsKeyField>
      <IsForeignKeyField>false</IsForeignKeyField>
      <IsIdentity>false</IsIdentity>
      <IsUpdatable>true</IsUpdatable>
      <!--IsResource>true</IsResource-->
      <Relation>
        <DDLType>enum.MaturityValueEnum</DDLType>
      </Relation>
    </Column>
    <Column>
      <ColumnName>STRIKEVALUE</ColumnName>
      <Ressource>STRIKEVALUE</Ressource>
      <Colspan>0</Colspan>
      <DataType>string</DataType>
      <Length>64</Length>
      <Scale>0</Scale>
      <IsMandatory>false</IsMandatory>
      <RegularExpression></RegularExpression>
      <Default></Default>
      <IsHide>false</IsHide>
      <IsHideInDataGrid>false</IsHideInDataGrid>
      <IsDataKeyField>false</IsDataKeyField>
      <IsKeyField>false</IsKeyField>
      <IsForeignKeyField>false</IsForeignKeyField>
      <IsIdentity>false</IsIdentity>
      <IsUpdatable>true</IsUpdatable>
      <!--IsResource>true</IsResource-->
      <Relation>
        <DDLType>enum.StrikeValueEnum</DDLType>
      </Relation>
    </Column>
    <Column>
      <ColumnName>SIDEVALUE</ColumnName>
      <Ressource>SIDEVALUE</Ressource>
      <Colspan>0</Colspan>
      <DataType>string</DataType>
      <Length>64</Length>
      <Scale>0</Scale>
      <IsMandatory>false</IsMandatory>
      <RegularExpression></RegularExpression>
      <Default></Default>
      <IsHide>false</IsHide>
      <IsHideInDataGrid>false</IsHideInDataGrid>
      <IsDataKeyField>false</IsDataKeyField>
      <IsKeyField>false</IsKeyField>
      <IsForeignKeyField>false</IsForeignKeyField>
      <IsIdentity>false</IsIdentity>
      <IsUpdatable>true</IsUpdatable>
      <!--IsResource>true</IsResource-->
      <Relation>
        <DDLType>enum.StrategySideEnum</DDLType>
      </Relation>
      <Information>
        <Type>information</Type>
        <LabelMessage>Msg_SIDEVALUEForINSTRUMENTOF</LabelMessage>
      </Information>
      <html_HR title="Side_Title" size="1"></html_HR>
    </Column>
    <Column>
      <ColumnName>QUANTITYVALUE</ColumnName>
      <Ressource>QUANTITYVALUE</Ressource>
      <Colspan>0</Colspan>
      <DataType>string</DataType>
      <Length>64</Length>
      <Scale>0</Scale>
      <IsMandatory>false</IsMandatory>
      <RegularExpression></RegularExpression>
      <Default></Default>
      <IsHide>false</IsHide>
      <IsHideInDataGrid>false</IsHideInDataGrid>
      <IsDataKeyField>false</IsDataKeyField>
      <IsKeyField>false</IsKeyField>
      <IsForeignKeyField>false</IsForeignKeyField>
      <IsIdentity>false</IsIdentity>
      <IsUpdatable>true</IsUpdatable>
      <!--IsResource>true</IsResource-->
      <Relation>
        <DDLType>enum.QuantityValueEnum</DDLType>
      </Relation>
      <html_HR title="Empty" size="1"></html_HR>
    </Column>
    <Column>
      <ColumnName>PRICEVALUE</ColumnName>
      <Ressource>PRICEVALUE</Ressource>
      <Colspan>0</Colspan>
      <DataType>string</DataType>
      <Length>64</Length>
      <Scale>0</Scale>
      <IsMandatory>false</IsMandatory>
      <RegularExpression></RegularExpression>
      <Default></Default>
      <IsHide>false</IsHide>
      <IsHideInDataGrid>false</IsHideInDataGrid>
      <IsDataKeyField>false</IsDataKeyField>
      <IsKeyField>false</IsKeyField>
      <IsForeignKeyField>false</IsForeignKeyField>
      <IsIdentity>false</IsIdentity>
      <IsUpdatable>true</IsUpdatable>
      <Relation>
        <DDLType>enum.PriceValueEnum</DDLType>
      </Relation>
    </Column>
    <Column>
      <ColumnName>IDAINS</ColumnName>
      <Ressource>IDAINS</Ressource>
      <DataType>int</DataType>
      <Length>10</Length>
      <Scale>0</Scale>
      <IsMandatory>true</IsMandatory>
      <RegularExpression></RegularExpression>
      <Default></Default>
      <IsHide>true</IsHide>
      <IsHideInDataGrid>true</IsHideInDataGrid>
      <IsKeyField>false</IsKeyField>
      <IsDataKeyField>false</IsDataKeyField>
      <IsIdentity>false</IsIdentity>
      <IsUpdatable>false</IsUpdatable>
      <Relation>
        <TableName>ACTOR</TableName>
        <AliasTableName>insa</AliasTableName>
        <ColumnRelation>
          <ColumnName>IDA</ColumnName>
          <DataType>int</DataType>
        </ColumnRelation>
        <ColumnSelect>
          <ColumnName>DISPLAYNAME</ColumnName>
          <Ressource>Display name</Ressource>
          <DataType>string</DataType>
        </ColumnSelect>
      </Relation>
    </Column>
    <Column>
      <ColumnName>DTINS</ColumnName>
      <Ressource>DTINS</Ressource>
      <DataType>date</DataType>
      <Length>8</Length>
      <Scale>0</Scale>
      <IsMandatory>true</IsMandatory>
      <RegularExpression></RegularExpression>
      <Default></Default>
      <IsHide>true</IsHide>
      <IsHideInDataGrid>true</IsHideInDataGrid>
      <IsKeyField>false</IsKeyField>
      <IsDataKeyField>false</IsDataKeyField>
      <IsIdentity>false</IsIdentity>
      <IsUpdatable>true</IsUpdatable>
      <Relation></Relation>
    </Column>
    <Column>
      <ColumnName>IDAUPD</ColumnName>
      <Ressource>IDAUPD</Ressource>
      <DataType>int</DataType>
      <Length>10</Length>
      <Scale>0</Scale>
      <IsMandatory>false</IsMandatory>
      <RegularExpression></RegularExpression>
      <Default></Default>
      <IsHide>true</IsHide>
      <IsHideInDataGrid>true</IsHideInDataGrid>
      <IsKeyField>false</IsKeyField>
      <IsDataKeyField>false</IsDataKeyField>
      <IsIdentity>false</IsIdentity>
      <IsUpdatable>false</IsUpdatable>
      <Relation>
        <TableName>ACTOR</TableName>
        <AliasTableName>upda</AliasTableName>
        <ColumnRelation>
          <ColumnName>IDA</ColumnName>
          <DataType>int</DataType>
        </ColumnRelation>
        <ColumnSelect>
          <ColumnName>DISPLAYNAME</ColumnName>
          <Ressource>Display name</Ressource>
          <DataType>string</DataType>
        </ColumnSelect>
      </Relation>
    </Column>
    <Column>
      <ColumnName>DTUPD</ColumnName>
      <Ressource>DTUPD</Ressource>
      <DataType>date</DataType>
      <Length>8</Length>
      <Scale>0</Scale>
      <IsMandatory>false</IsMandatory>
      <RegularExpression></RegularExpression>
      <Default></Default>
      <IsHide>true</IsHide>
      <IsHideInDataGrid>true</IsHideInDataGrid>
      <IsKeyField>false</IsKeyField>
      <IsDataKeyField>false</IsDataKeyField>
      <IsIdentity>false</IsIdentity>
      <IsUpdatable>true</IsUpdatable>
      <Relation></Relation>
    </Column>
    <Column>
      <ColumnName>EXTLLINK</ColumnName>
      <Ressource>EXTLLINK</Ressource>
      <Colspan>3</Colspan>
      <DataType>string</DataType>
      <Length>128</Length>
      <Scale>0</Scale>
      <IsMandatory>false</IsMandatory>
      <RegularExpression></RegularExpression>
      <Default></Default>
      <IsHide>false</IsHide>
      <IsHideInDataGrid>false</IsHideInDataGrid>
      <IsDataKeyField>false</IsDataKeyField>
      <IsKeyField>false</IsKeyField>
      <IsForeignKeyField>false</IsForeignKeyField>
      <IsIdentity>false</IsIdentity>
      <IsUpdatable>true</IsUpdatable>
      <Relation></Relation>
      <html_BLOCK title="ExtlLink_" columnbyrow="3"></html_BLOCK>
    </Column>
    <Column>
      <ColumnName>ROWATTRIBUT</ColumnName>
      <Ressource>ROWATTRIBUT</Ressource>
      <DataType>string</DataType>
      <Length>1</Length>
      <Scale>0</Scale>
      <IsMandatory>false</IsMandatory>
      <RegularExpression></RegularExpression>
      <Default></Default>
      <IsHide>true</IsHide>
      <IsHideInDataGrid>true</IsHideInDataGrid>
      <IsDataKeyField>false</IsDataKeyField>
      <IsKeyField>false</IsKeyField>
      <IsForeignKeyField>false</IsForeignKeyField>
      <IsIdentity>false</IsIdentity>
      <IsUpdatable>true</IsUpdatable>
      <Relation></Relation>
    </Column>
    <Column>
      <ColumnName>ROWVERSION</ColumnName>
      <Ressource>ROWVERSION</Ressource>
      <DataType>string</DataType>
      <Length>8</Length>
      <Scale>0</Scale>
      <IsMandatory>true</IsMandatory>
      <RegularExpression></RegularExpression>
      <Default></Default>
      <IsHide>true</IsHide>
      <IsHideInDataGrid>true</IsHideInDataGrid>
      <IsDataKeyField>true</IsDataKeyField>
      <IsKeyField>false</IsKeyField>
      <IsForeignKeyField>false</IsForeignKeyField>
      <IsIdentity>false</IsIdentity>
      <IsUpdatable>true</IsUpdatable>
      <Relation></Relation>
    </Column>
  </Referential>
</Referentials>